[
  {
    "token_id": 0,
    "sentence_id": 1,
    "token_body": "Artificial",
    "token_type": "text",
    "sentence_token_index": 0,
    "difficulty_level": null,
    "explanation": null,
    "pos_tag": null,
    "lemma": null,
    "is_grammar_marker": false
  },
  {
    "token_id": 1,
    "sentence_id": 1,
    "token_body": " ",
    "token_type": "space",
    "sentence_token_index": 1,
    "difficulty_level": null,
    "explanation": null,
    "pos_tag": null,
    "lemma": null,
    "is_grammar_marker": false
  },
  {
    "token_id": 2,
    "sentence_id": 1,
    "token_body": "intelligence",
    "token_type": "text",
    "sentence_token_index": 2,
    "difficulty_level": null,
    "explanation": null,
    "pos_tag": null,
    "lemma": null,
    "is_grammar_marker": false
  },
  {
    "token_id": 3,
    "sentence_id": 1,
    "token_body": " ",
    "token_type": "space",
    "sentence_token_index": 3,
    "difficulty_level": null,
    "explanation": null,
    "pos_tag": null,
    "lemma": null,
    "is_grammar_marker": false
  },
  {
    "token_id": 4,
    "sentence_id": 1,
    "token_body": "has",
    "token_type": "text",
    "sentence_token_index": 4,
    "difficulty_level": null,
    "explanation": null,
    "pos_tag": null,
    "lemma": null,
    "is_grammar_marker": false
  },
  {
    "token_id": 5,
    "sentence_id": 1,
    "token_body": " ",
    "token_type": "space",
    "sentence_token_index": 5,
    "difficulty_level": null,
    "explanation": null,
    "pos_tag": null,
    "lemma": null,
    "is_grammar_marker": false
  },
  {
    "token_id": 6,
    "sentence_id": 1,
    "token_body": "revolutionized",
    "token_type": "text",
    "sentence_token_index": 6,
    "difficulty_level": null,
    "explanation": null,
    "pos_tag": null,
    "lemma": null,
    "is_grammar_marker": false
  },
  {
    "token_id": 7,
    "sentence_id": 1,
    "token_body": " ",
    "token_type": "space",
    "sentence_token_index": 7,
    "difficulty_level": null,
    "explanation": null,
    "pos_tag": null,
    "lemma": null,
    "is_grammar_marker": false
  },
  {
    "token_id": 8,
    "sentence_id": 1,
    "token_body": "the",
    "token_type": "text",
    "sentence_token_index": 8,
    "difficulty_level": null,
    "explanation": null,
    "pos_tag": null,
    "lemma": null,
    "is_grammar_marker": false
  },
  {
    "token_id": 9,
    "sentence_id": 1,
    "token_body": " ",
    "token_type": "space",
    "sentence_token_index": 9,
    "difficulty_level": null,
    "explanation": null,
    "pos_tag": null,
    "lemma": null,
    "is_grammar_marker": false
  },
  {
    "token_id": 10,
    "sentence_id": 1,
    "token_body": "way",
    "token_type": "text",
    "sentence_token_index": 10,
    "difficulty_level": null,
    "explanation": null,
    "pos_tag": null,
    "lemma": null,
    "is_grammar_marker": false
  },
  {
    "token_id": 11,
    "sentence_id": 1,
    "token_body": " ",
    "token_type": "space",
    "sentence_token_index": 11,
    "difficulty_level": null,
    "explanation": null,
    "pos_tag": null,
    "lemma": null,
    "is_grammar_marker": false
  },
  {
    "token_id": 12,
    "sentence_id": 1,
    "token_body": "we",
    "token_type": "text",
    "sentence_token_index": 12,
    "difficulty_level": null,
    "explanation": null,
    "pos_tag": null,
    "lemma": null,
    "is_grammar_marker": false
  },
  {
    "token_id": 13,
    "sentence_id": 1,
    "token_body": " ",
    "token_type": "space",
    "sentence_token_index": 13,
    "difficulty_level": null,
    "explanation": null,
    "pos_tag": null,
    "lemma": null,
    "is_grammar_marker": false
  },
  {
    "token_id": 14,
    "sentence_id": 1,
    "token_body": "interact",
    "token_type": "text",
    "sentence_token_index": 14,
    "difficulty_level": null,
    "explanation": null,
    "pos_tag": null,
    "lemma": null,
    "is_grammar_marker": false
  },
  {
    "token_id": 15,
    "sentence_id": 1,
    "token_body": " ",
    "token_type": "space",
    "sentence_token_index": 15,
    "difficulty_level": null,
    "explanation": null,
    "pos_tag": null,
    "lemma": null,
    "is_grammar_marker": false
  },
  {
    "token_id": 16,
    "sentence_id": 1,
    "token_body": "with",
    "token_type": "text",
    "sentence_token_index": 16,
    "difficulty_level": null,
    "explanation": null,
    "pos_tag": null,
    "lemma": null,
    "is_grammar_marker": false
  },
  {
    "token_id": 17,
    "sentence_id": 1,
    "token_body": " ",
    "token_type": "space",
    "sentence_token_index": 17,
    "difficulty_level": null,
    "explanation": null,
    "pos_tag": null,
    "lemma": null,
    "is_grammar_marker": false
  },
  {
    "token_id": 18,
    "sentence_id": 1,
    "token_body": "technology",
    "token_type": "text",
    "sentence_token_index": 18,
    "difficulty_level": null,
    "explanation": null,
    "pos_tag": null,
    "lemma": null,
    "is_grammar_marker": false
  },
  {
    "token_id": 19,
    "sentence_id": 1,
    "token_body": " ",
    "token_type": "space",
    "sentence_token_index": 19,
    "difficulty_level": null,
    "explanation": null,
    "pos_tag": null,
    "lemma": null,
    "is_grammar_marker": false
  },
  {
    "token_id": 20,
    "sentence_id": 1,
    "token_body": "in",
    "token_type": "text",
    "sentence_token_index": 20,
    "difficulty_level": null,
    "explanation": null,
    "pos_tag": null,
    "lemma": null,
    "is_grammar_marker": false
  },
  {
    "token_id": 21,
    "sentence_id": 1,
    "token_body": " ",
    "token_type": "space",
    "sentence_token_index": 21,
    "difficulty_level": null,
    "explanation": null,
    "pos_tag": null,
    "lemma": null,
    "is_grammar_marker": false
  },
  {
    "token_id": 22,
    "sentence_id": 1,
    "token_body": "the",
    "token_type": "text",
    "sentence_token_index": 22,
    "difficulty_level": null,
    "explanation": null,
    "pos_tag": null,
    "lemma": null,
    "is_grammar_marker": false
  },
  {
    "token_id": 23,
    "sentence_id": 1,
    "token_body": " ",
    "token_type": "space",
    "sentence_token_index": 23,
    "difficulty_level": null,
    "explanation": null,
    "pos_tag": null,
    "lemma": null,
    "is_grammar_marker": false
  },
  {
    "token_id": 24,
    "sentence_id": 1,
    "token_body": "modern",
    "token_type": "text",
    "sentence_token_index": 24,
    "difficulty_level": null,
    "explanation": null,
    "pos_tag": null,
    "lemma": null,
    "is_grammar_marker": false
  },
  {
    "token_id": 25,
    "sentence_id": 1,
    "token_body": " ",
    "token_type": "space",
    "sentence_token_index": 25,
    "difficulty_level": null,
    "explanation": null,
    "pos_tag": null,
    "lemma": null,
    "is_grammar_marker": false
  },
  {
    "token_id": 26,
    "sentence_id": 1,
    "token_body": "world",
    "token_type": "text",
    "sentence_token_index": 26,
    "difficulty_level": null,
    "explanation": null,
    "pos_tag": null,
    "lemma": null,
    "is_grammar_marker": false
  },
  {
    "token_id": 27,
    "sentence_id": 1,
    "token_body": ".",
    "token_type": "punctuation",
    "sentence_token_index": 27,
    "difficulty_level": null,
    "explanation": null,
    "pos_tag": null,
    "lemma": null,
    "is_grammar_marker": false
  },
  {
    "token_id": 28,
    "sentence_id": 2,
    "token_body": "Machine",
    "token_type": "text",
    "sentence_token_index": 0,
    "difficulty_level": null,
    "explanation": null,
    "pos_tag": null,
    "lemma": null,
    "is_grammar_marker": false
  },
  {
    "token_id": 29,
    "sentence_id": 2,
    "token_body": " ",
    "token_type": "space",
    "sentence_token_index": 1,
    "difficulty_level": null,
    "explanation": null,
    "pos_tag": null,
    "lemma": null,
    "is_grammar_marker": false
  },
  {
    "token_id": 30,
    "sentence_id": 2,
    "token_body": "learning",
    "token_type": "text",
    "sentence_token_index": 2,
    "difficulty_level": null,
    "explanation": null,
    "pos_tag": null,
    "lemma": null,
    "is_grammar_marker": false
  },
  {
    "token_id": 31,
    "sentence_id": 2,
    "token_body": " ",
    "token_type": "space",
    "sentence_token_index": 3,
    "difficulty_level": null,
    "explanation": null,
    "pos_tag": null,
    "lemma": null,
    "is_grammar_marker": false
  },
  {
    "token_id": 32,
    "sentence_id": 2,
    "token_body": "algorithms",
    "token_type": "text",
    "sentence_token_index": 4,
    "difficulty_level": null,
    "explanation": null,
    "pos_tag": null,
    "lemma": null,
    "is_grammar_marker": false
  },
  {
    "token_id": 33,
    "sentence_id": 2,
    "token_body": " ",
    "token_type": "space",
    "sentence_token_index": 5,
    "difficulty_level": null,
    "explanation": null,
    "pos_tag": null,
    "lemma": null,
    "is_grammar_marker": false
  },
  {
    "token_id": 34,
    "sentence_id": 2,
    "token_body": "can",
    "token_type": "text",
    "sentence_token_index": 6,
    "difficulty_level": null,
    "explanation": null,
    "pos_tag": null,
    "lemma": null,
    "is_grammar_marker": false
  },
  {
    "token_id": 35,
    "sentence_id": 2,
    "token_body": " ",
    "token_type": "space",
    "sentence_token_index": 7,
    "difficulty_level": null,
    "explanation": null,
    "pos_tag": null,
    "lemma": null,
    "is_grammar_marker": false
  },
  {
    "token_id": 36,
    "sentence_id": 2,
    "token_body": "now",
    "token_type": "text",
    "sentence_token_index": 8,
    "difficulty_level": null,
    "explanation": null,
    "pos_tag": null,
    "lemma": null,
    "is_grammar_marker": false
  },
  {
    "token_id": 37,
    "sentence_id": 2,
    "token_body": " ",
    "token_type": "space",
    "sentence_token_index": 9,
    "difficulty_level": null,
    "explanation": null,
    "pos_tag": null,
    "lemma": null,
    "is_grammar_marker": false
  },
  {
    "token_id": 38,
    "sentence_id": 2,
    "token_body": "process",
    "token_type": "text",
    "sentence_token_index": 10,
    "difficulty_level": null,
    "explanation": null,
    "pos_tag": null,
    "lemma": null,
    "is_grammar_marker": false
  },
  {
    "token_id": 39,
    "sentence_id": 2,
    "token_body": " ",
    "token_type": "space",
    "sentence_token_index": 11,
    "difficulty_level": null,
    "explanation": null,
    "pos_tag": null,
    "lemma": null,
    "is_grammar_marker": false
  },
  {
    "token_id": 40,
    "sentence_id": 2,
    "token_body": "vast",
    "token_type": "text",
    "sentence_token_index": 12,
    "difficulty_level": null,
    "explanation": null,
    "pos_tag": null,
    "lemma": null,
    "is_grammar_marker": false
  },
  {
    "token_id": 41,
    "sentence_id": 2,
    "token_body": " ",
    "token_type": "space",
    "sentence_token_index": 13,
    "difficulty_level": null,
    "explanation": null,
    "pos_tag": null,
    "lemma": null,
    "is_grammar_marker": false
  },
  {
    "token_id": 42,
    "sentence_id": 2,
    "token_body": "amounts",
    "token_type": "text",
    "sentence_token_index": 14,
    "difficulty_level": null,
    "explanation": null,
    "pos_tag": null,
    "lemma": null,
    "is_grammar_marker": false
  },
  {
    "token_id": 43,
    "sentence_id": 2,
    "token_body": " ",
    "token_type": "space",
    "sentence_token_index": 15,
    "difficulty_level": null,
    "explanation": null,
    "pos_tag": null,
    "lemma": null,
    "is_grammar_marker": false
  },
  {
    "token_id": 44,
    "sentence_id": 2,
    "token_body": "of",
    "token_type": "text",
    "sentence_token_index": 16,
    "difficulty_level": null,
    "explanation": null,
    "pos_tag": null,
    "lemma": null,
    "is_grammar_marker": false
  },
  {
    "token_id": 45,
    "sentence_id": 2,
    "token_body": " ",
    "token_type": "space",
    "sentence_token_index": 17,
    "difficulty_level": null,
    "explanation": null,
    "pos_tag": null,
    "lemma": null,
    "is_grammar_marker": false
  },
  {
    "token_id": 46,
    "sentence_id": 2,
    "token_body": "data",
    "token_type": "text",
    "sentence_token_index": 18,
    "difficulty_level": null,
    "explanation": null,
    "pos_tag": null,
    "lemma": null,
    "is_grammar_marker": false
  },
  {
    "token_id": 47,
    "sentence_id": 2,
    "token_body": " ",
    "token_type": "space",
    "sentence_token_index": 19,
    "difficulty_level": null,
    "explanation": null,
    "pos_tag": null,
    "lemma": null,
    "is_grammar_marker": false
  },
  {
    "token_id": 48,
    "sentence_id": 2,
    "token_body": "and",
    "token_type": "text",
    "sentence_token_index": 20,
    "difficulty_level": null,
    "explanation": null,
    "pos_tag": null,
    "lemma": null,
    "is_grammar_marker": false
  },
  {
    "token_id": 49,
    "sentence_id": 2,
    "token_body": " ",
    "token_type": "space",
    "sentence_token_index": 21,
    "difficulty_level": null,
    "explanation": null,
    "pos_tag": null,
    "lemma": null,
    "is_grammar_marker": false
  },
  {
    "token_id": 50,
    "sentence_id": 2,
    "token_body": "identify",
    "token_type": "text",
    "sentence_token_index": 22,
    "difficulty_level": null,
    "explanation": null,
    "pos_tag": null,
    "lemma": null,
    "is_grammar_marker": false
  },
  {
    "token_id": 51,
    "sentence_id": 2,
    "token_body": " ",
    "token_type": "space",
    "sentence_token_index": 23,
    "difficulty_level": null,
    "explanation": null,
    "pos_tag": null,
    "lemma": null,
    "is_grammar_marker": false
  },
  {
    "token_id": 52,
    "sentence_id": 2,
    "token_body": "complex",
    "token_type": "text",
    "sentence_token_index": 24,
    "difficulty_level": null,
    "explanation": null,
    "pos_tag": null,
    "lemma": null,
    "is_grammar_marker": false
  },
  {
    "token_id": 53,
    "sentence_id": 2,
    "token_body": " ",
    "token_type": "space",
    "sentence_token_index": 25,
    "difficulty_level": null,
    "explanation": null,
    "pos_tag": null,
    "lemma": null,
    "is_grammar_marker": false
  },
  {
    "token_id": 54,
    "sentence_id": 2,
    "token_body": "patterns",
    "token_type": "text",
    "sentence_token_index": 26,
    "difficulty_level": null,
    "explanation": null,
    "pos_tag": null,
    "lemma": null,
    "is_grammar_marker": false
  },
  {
    "token_id": 55,
    "sentence_id": 2,
    "token_body": " ",
    "token_type": "space",
    "sentence_token_index": 27,
    "difficulty_level": null,
    "explanation": null,
    "pos_tag": null,
    "lemma": null,
    "is_grammar_marker": false
  },
  {
    "token_id": 56,
    "sentence_id": 2,
    "token_body": "that",
    "token_type": "text",
    "sentence_token_index": 28,
    "difficulty_level": null,
    "explanation": null,
    "pos_tag": null,
    "lemma": null,
    "is_grammar_marker": false
  },
  {
    "token_id": 57,
    "sentence_id": 2,
    "token_body": " ",
    "token_type": "space",
    "sentence_token_index": 29,
    "difficulty_level": null,
    "explanation": null,
    "pos_tag": null,
    "lemma": null,
    "is_grammar_marker": false
  },
  {
    "token_id": 58,
    "sentence_id": 2,
    "token_body": "humans",
    "token_type": "text",
    "sentence_token_index": 30,
    "difficulty_level": null,
    "explanation": null,
    "pos_tag": null,
    "lemma": null,
    "is_grammar_marker": false
  },
  {
    "token_id": 59,
    "sentence_id": 2,
    "token_body": " ",
    "token_type": "space",
    "sentence_token_index": 31,
    "difficulty_level": null,
    "explanation": null,
    "pos_tag": null,
    "lemma": null,
    "is_grammar_marker": false
  },
  {
    "token_id": 60,
    "sentence_id": 2,
    "token_body": "might",
    "token_type": "text",
    "sentence_token_index": 32,
    "difficulty_level": null,
    "explanation": null,
    "pos_tag": null,
    "lemma": null,
    "is_grammar_marker": false
  },
  {
    "token_id": 61,
    "sentence_id": 2,
    "token_body": " ",
    "token_type": "space",
    "sentence_token_index": 33,
    "difficulty_level": null,
    "explanation": null,
    "pos_tag": null,
    "lemma": null,
    "is_grammar_marker": false
  },
  {
    "token_id": 62,
    "sentence_id": 2,
    "token_body": "miss",
    "token_type": "text",
    "sentence_token_index": 34,
    "difficulty_level": null,
    "explanation": null,
    "pos_tag": null,
    "lemma": null,
    "is_grammar_marker": false
  },
  {
    "token_id": 63,
    "sentence_id": 2,
    "token_body": ".",
    "token_type": "punctuation",
    "sentence_token_index": 35,
    "difficulty_level": null,
    "explanation": null,
    "pos_tag": null,
    "lemma": null,
    "is_grammar_marker": false
  },
  {
    "token_id": 64,
    "sentence_id": 3,
    "token_body": "Natural",
    "token_type": "text",
    "sentence_token_index": 0,
    "difficulty_level": null,
    "explanation": null,
    "pos_tag": null,
    "lemma": null,
    "is_grammar_marker": false
  },
  {
    "token_id": 65,
    "sentence_id": 3,
    "token_body": " ",
    "token_type": "space",
    "sentence_token_index": 1,
    "difficulty_level": null,
    "explanation": null,
    "pos_tag": null,
    "lemma": null,
    "is_grammar_marker": false
  },
  {
    "token_id": 66,
    "sentence_id": 3,
    "token_body": "language",
    "token_type": "text",
    "sentence_token_index": 2,
    "difficulty_level": null,
    "explanation": null,
    "pos_tag": null,
    "lemma": null,
    "is_grammar_marker": false
  },
  {
    "token_id": 67,
    "sentence_id": 3,
    "token_body": " ",
    "token_type": "space",
    "sentence_token_index": 3,
    "difficulty_level": null,
    "explanation": null,
    "pos_tag": null,
    "lemma": null,
    "is_grammar_marker": false
  },
  {
    "token_id": 68,
    "sentence_id": 3,
    "token_body": "processing",
    "token_type": "text",
    "sentence_token_index": 4,
    "difficulty_level": null,
    "explanation": null,
    "pos_tag": null,
    "lemma": null,
    "is_grammar_marker": false
  },
  {
    "token_id": 69,
    "sentence_id": 3,
    "token_body": " ",
    "token_type": "space",
    "sentence_token_index": 5,
    "difficulty_level": null,
    "explanation": null,
    "pos_tag": null,
    "lemma": null,
    "is_grammar_marker": false
  },
  {
    "token_id": 70,
    "sentence_id": 3,
    "token_body": "enables",
    "token_type": "text",
    "sentence_token_index": 6,
    "difficulty_level": null,
    "explanation": null,
    "pos_tag": null,
    "lemma": null,
    "is_grammar_marker": false
  },
  {
    "token_id": 71,
    "sentence_id": 3,
    "token_body": " ",
    "token_type": "space",
    "sentence_token_index": 7,
    "difficulty_level": null,
    "explanation": null,
    "pos_tag": null,
    "lemma": null,
    "is_grammar_marker": false
  },
  {
    "token_id": 72,
    "sentence_id": 3,
    "token_body": "computers",
    "token_type": "text",
    "sentence_token_index": 8,
    "difficulty_level": null,
    "explanation": null,
    "pos_tag": null,
    "lemma": null,
    "is_grammar_marker": false
  },
  {
    "token_id": 73,
    "sentence_id": 3,
    "token_body": " ",
    "token_type": "space",
    "sentence_token_index": 9,
    "difficulty_level": null,
    "explanation": null,
    "pos_tag": null,
    "lemma": null,
    "is_grammar_marker": false
  },
  {
    "token_id": 74,
    "sentence_id": 3,
    "token_body": "to",
    "token_type": "text",
    "sentence_token_index": 10,
    "difficulty_level": null,
    "explanation": null,
    "pos_tag": null,
    "lemma": null,
    "is_grammar_marker": false
  },
  {
    "token_id": 75,
    "sentence_id": 3,
    "token_body": " ",
    "token_type": "space",
    "sentence_token_index": 11,
    "difficulty_level": null,
    "explanation": null,
    "pos_tag": null,
    "lemma": null,
    "is_grammar_marker": false
  },
  {
    "token_id": 76,
    "sentence_id": 3,
    "token_body": "understand",
    "token_type": "text",
    "sentence_token_index": 12,
    "difficulty_level": null,
    "explanation": null,
    "pos_tag": null,
    "lemma": null,
    "is_grammar_marker": false
  },
  {
    "token_id": 77,
    "sentence_id": 3,
    "token_body": " ",
    "token_type": "space",
    "sentence_token_index": 13,
    "difficulty_level": null,
    "explanation": null,
    "pos_tag": null,
    "lemma": null,
    "is_grammar_marker": false
  },
  {
    "token_id": 78,
    "sentence_id": 3,
    "token_body": "and",
    "token_type": "text",
    "sentence_token_index": 14,
    "difficulty_level": null,
    "explanation": null,
    "pos_tag": null,
    "lemma": null,
    "is_grammar_marker": false
  },
  {
    "token_id": 79,
    "sentence_id": 3,
    "token_body": " ",
    "token_type": "space",
    "sentence_token_index": 15,
    "difficulty_level": null,
    "explanation": null,
    "pos_tag": null,
    "lemma": null,
    "is_grammar_marker": false
  },
  {
    "token_id": 80,
    "sentence_id": 3,
    "token_body": "generate",
    "token_type": "text",
    "sentence_token_index": 16,
    "difficulty_level": null,
    "explanation": null,
    "pos_tag": null,
    "lemma": null,
    "is_grammar_marker": false
  },
  {
    "token_id": 81,
    "sentence_id": 3,
    "token_body": " ",
    "token_type": "space",
    "sentence_token_index": 17,
    "difficulty_level": null,
    "explanation": null,
    "pos_tag": null,
    "lemma": null,
    "is_grammar_marker": false
  },
  {
    "token_id": 82,
    "sentence_id": 3,
    "token_body": "human",
    "token_type": "text",
    "sentence_token_index": 18,
    "difficulty_level": null,
    "explanation": null,
    "pos_tag": null,
    "lemma": null,
    "is_grammar_marker": false
  },
  {
    "token_id": 83,
    "sentence_id": 3,
    "token_body": " ",
    "token_type": "space",
    "sentence_token_index": 19,
    "difficulty_level": null,
    "explanation": null,
    "pos_tag": null,
    "lemma": null,
    "is_grammar_marker": false
  },
  {
    "token_id": 84,
    "sentence_id": 3,
    "token_body": "language",
    "token_type": "text",
    "sentence_token_index": 20,
    "difficulty_level": null,
    "explanation": null,
    "pos_tag": null,
    "lemma": null,
    "is_grammar_marker": false
  },
  {
    "token_id": 85,
    "sentence_id": 3,
    "token_body": " ",
    "token_type": "space",
    "sentence_token_index": 21,
    "difficulty_level": null,
    "explanation": null,
    "pos_tag": null,
    "lemma": null,
    "is_grammar_marker": false
  },
  {
    "token_id": 86,
    "sentence_id": 3,
    "token_body": "with",
    "token_type": "text",
    "sentence_token_index": 22,
    "difficulty_level": null,
    "explanation": null,
    "pos_tag": null,
    "lemma": null,
    "is_grammar_marker": false
  },
  {
    "token_id": 87,
    "sentence_id": 3,
    "token_body": " ",
    "token_type": "space",
    "sentence_token_index": 23,
    "difficulty_level": null,
    "explanation": null,
    "pos_tag": null,
    "lemma": null,
    "is_grammar_marker": false
  },
  {
    "token_id": 88,
    "sentence_id": 3,
    "token_body": "remarkable",
    "token_type": "text",
    "sentence_token_index": 24,
    "difficulty_level": null,
    "explanation": null,
    "pos_tag": null,
    "lemma": null,
    "is_grammar_marker": false
  },
  {
    "token_id": 89,
    "sentence_id": 3,
    "token_body": " ",
    "token_type": "space",
    "sentence_token_index": 25,
    "difficulty_level": null,
    "explanation": null,
    "pos_tag": null,
    "lemma": null,
    "is_grammar_marker": false
  },
  {
    "token_id": 90,
    "sentence_id": 3,
    "token_body": "accuracy",
    "token_type": "text",
    "sentence_token_index": 26,
    "difficulty_level": null,
    "explanation": null,
    "pos_tag": null,
    "lemma": null,
    "is_grammar_marker": false
  },
  {
    "token_id": 91,
    "sentence_id": 3,
    "token_body": ".",
    "token_type": "punctuation",
    "sentence_token_index": 27,
    "difficulty_level": null,
    "explanation": null,
    "pos_tag": null,
    "lemma": null,
    "is_grammar_marker": false
  },
  {
    "token_id": 92,
    "sentence_id": 4,
    "token_body": "Deep",
    "token_type": "text",
    "sentence_token_index": 0,
    "difficulty_level": null,
    "explanation": null,
    "pos_tag": null,
    "lemma": null,
    "is_grammar_marker": false
  },
  {
    "token_id": 93,
    "sentence_id": 4,
    "token_body": " ",
    "token_type": "space",
    "sentence_token_index": 1,
    "difficulty_level": null,
    "explanation": null,
    "pos_tag": null,
    "lemma": null,
    "is_grammar_marker": false
  },
  {
    "token_id": 94,
    "sentence_id": 4,
    "token_body": "learning",
    "token_type": "text",
    "sentence_token_index": 2,
    "difficulty_level": null,
    "explanation": null,
    "pos_tag": null,
    "lemma": null,
    "is_grammar_marker": false
  },
  {
    "token_id": 95,
    "sentence_id": 4,
    "token_body": " ",
    "token_type": "space",
    "sentence_token_index": 3,
    "difficulty_level": null,
    "explanation": null,
    "pos_tag": null,
    "lemma": null,
    "is_grammar_marker": false
  },
  {
    "token_id": 96,
    "sentence_id": 4,
    "token_body": "models",
    "token_type": "text",
    "sentence_token_index": 4,
    "difficulty_level": null,
    "explanation": null,
    "pos_tag": null,
    "lemma": null,
    "is_grammar_marker": false
  },
  {
    "token_id": 97,
    "sentence_id": 4,
    "token_body": " ",
    "token_type": "space",
    "sentence_token_index": 5,
    "difficulty_level": null,
    "explanation": null,
    "pos_tag": null,
    "lemma": null,
    "is_grammar_marker": false
  },
  {
    "token_id": 98,
    "sentence_id": 4,
    "token_body": "have",
    "token_type": "text",
    "sentence_token_index": 6,
    "difficulty_level": null,
    "explanation": null,
    "pos_tag": null,
    "lemma": null,
    "is_grammar_marker": false
  },
  {
    "token_id": 99,
    "sentence_id": 4,
    "token_body": " ",
    "token_type": "space",
    "sentence_token_index": 7,
    "difficulty_level": null,
    "explanation": null,
    "pos_tag": null,
    "lemma": null,
    "is_grammar_marker": false
  },
  {
    "token_id": 100,
    "sentence_id": 4,
    "token_body": "achieved",
    "token_type": "text",
    "sentence_token_index": 8,
    "difficulty_level": null,
    "explanation": null,
    "pos_tag": null,
    "lemma": null,
    "is_grammar_marker": false
  },
  {
    "token_id": 101,
    "sentence_id": 4,
    "token_body": " ",
    "token_type": "space",
    "sentence_token_index": 9,
    "difficulty_level": null,
    "explanation": null,
    "pos_tag": null,
    "lemma": null,
    "is_grammar_marker": false
  },
  {
    "token_id": 102,
    "sentence_id": 4,
    "token_body": "breakthrough",
    "token_type": "text",
    "sentence_token_index": 10,
    "difficulty_level": null,
    "explanation": null,
    "pos_tag": null,
    "lemma": null,
    "is_grammar_marker": false
  },
  {
    "token_id": 103,
    "sentence_id": 4,
    "token_body": " ",
    "token_type": "space",
    "sentence_token_index": 11,
    "difficulty_level": null,
    "explanation": null,
    "pos_tag": null,
    "lemma": null,
    "is_grammar_marker": false
  },
  {
    "token_id": 104,
    "sentence_id": 4,
    "token_body": "performance",
    "token_type": "text",
    "sentence_token_index": 12,
    "difficulty_level": null,
    "explanation": null,
    "pos_tag": null,
    "lemma": null,
    "is_grammar_marker": false
  },
  {
    "token_id": 105,
    "sentence_id": 4,
    "token_body": " ",
    "token_type": "space",
    "sentence_token_index": 13,
    "difficulty_level": null,
    "explanation": null,
    "pos_tag": null,
    "lemma": null,
    "is_grammar_marker": false
  },
  {
    "token_id": 106,
    "sentence_id": 4,
    "token_body": "in",
    "token_type": "text",
    "sentence_token_index": 14,
    "difficulty_level": null,
    "explanation": null,
    "pos_tag": null,
    "lemma": null,
    "is_grammar_marker": false
  },
  {
    "token_id": 107,
    "sentence_id": 4,
    "token_body": " ",
    "token_type": "space",
    "sentence_token_index": 15,
    "difficulty_level": null,
    "explanation": null,
    "pos_tag": null,
    "lemma": null,
    "is_grammar_marker": false
  },
  {
    "token_id": 108,
    "sentence_id": 4,
    "token_body": "computer",
    "token_type": "text",
    "sentence_token_index": 16,
    "difficulty_level": null,
    "explanation": null,
    "pos_tag": null,
    "lemma": null,
    "is_grammar_marker": false
  },
  {
    "token_id": 109,
    "sentence_id": 4,
    "token_body": " ",
    "token_type": "space",
    "sentence_token_index": 17,
    "difficulty_level": null,
    "explanation": null,
    "pos_tag": null,
    "lemma": null,
    "is_grammar_marker": false
  },
  {
    "token_id": 110,
    "sentence_id": 4,
    "token_body": "vision",
    "token_type": "text",
    "sentence_token_index": 18,
    "difficulty_level": null,
    "explanation": null,
    "pos_tag": null,
    "lemma": null,
    "is_grammar_marker": false
  },
  {
    "token_id": 111,
    "sentence_id": 4,
    "token_body": ",",
    "token_type": "punctuation",
    "sentence_token_index": 19,
    "difficulty_level": null,
    "explanation": null,
    "pos_tag": null,
    "lemma": null,
    "is_grammar_marker": false
  },
  {
    "token_id": 112,
    "sentence_id": 4,
    "token_body": " ",
    "token_type": "space",
    "sentence_token_index": 20,
    "difficulty_level": null,
    "explanation": null,
    "pos_tag": null,
    "lemma": null,
    "is_grammar_marker": false
  },
  {
    "token_id": 113,
    "sentence_id": 4,
    "token_body": "speech",
    "token_type": "text",
    "sentence_token_index": 21,
    "difficulty_level": null,
    "explanation": null,
    "pos_tag": null,
    "lemma": null,
    "is_grammar_marker": false
  },
  {
    "token_id": 114,
    "sentence_id": 4,
    "token_body": " ",
    "token_type": "space",
    "sentence_token_index": 22,
    "difficulty_level": null,
    "explanation": null,
    "pos_tag": null,
    "lemma": null,
    "is_grammar_marker": false
  },
  {
    "token_id": 115,
    "sentence_id": 4,
    "token_body": "recognition",
    "token_type": "text",
    "sentence_token_index": 23,
    "difficulty_level": null,
    "explanation": null,
    "pos_tag": null,
    "lemma": null,
    "is_grammar_marker": false
  },
  {
    "token_id": 116,
    "sentence_id": 4,
    "token_body": ",",
    "token_type": "punctuation",
    "sentence_token_index": 24,
    "difficulty_level": null,
    "explanation": null,
    "pos_tag": null,
    "lemma": null,
    "is_grammar_marker": false
  },
  {
    "token_id": 117,
    "sentence_id": 4,
    "token_body": " ",
    "token_type": "space",
    "sentence_token_index": 25,
    "difficulty_level": null,
    "explanation": null,
    "pos_tag": null,
    "lemma": null,
    "is_grammar_marker": false
  },
  {
    "token_id": 118,
    "sentence_id": 4,
    "token_body": "and",
    "token_type": "text",
    "sentence_token_index": 26,
    "difficulty_level": null,
    "explanation": null,
    "pos_tag": null,
    "lemma": null,
    "is_grammar_marker": false
  },
  {
    "token_id": 119,
    "sentence_id": 4,
    "token_body": " ",
    "token_type": "space",
    "sentence_token_index": 27,
    "difficulty_level": null,
    "explanation": null,
    "pos_tag": null,
    "lemma": null,
    "is_grammar_marker": false
  },
  {
    "token_id": 120,
    "sentence_id": 4,
    "token_body": "autonomous",
    "token_type": "text",
    "sentence_token_index": 28,
    "difficulty_level": null,
    "explanation": null,
    "pos_tag": null,
    "lemma": null,
    "is_grammar_marker": false
  },
  {
    "token_id": 121,
    "sentence_id": 4,
    "token_body": " ",
    "token_type": "space",
    "sentence_token_index": 29,
    "difficulty_level": null,
    "explanation": null,
    "pos_tag": null,
    "lemma": null,
    "is_grammar_marker": false
  },
  {
    "token_id": 122,
    "sentence_id": 4,
    "token_body": "systems",
    "token_type": "text",
    "sentence_token_index": 30,
    "difficulty_level": null,
    "explanation": null,
    "pos_tag": null,
    "lemma": null,
    "is_grammar_marker": false
  },
  {
    "token_id": 123,
    "sentence_id": 4,
    "token_body": ".",
    "token_type": "punctuation",
    "sentence_token_index": 31,
    "difficulty_level": null,
    "explanation": null,
    "pos_tag": null,
    "lemma": null,
    "is_grammar_marker": false
  },
  {
    "token_id": 124,
    "sentence_id": 5,
    "token_body": "The",
    "token_type": "text",
    "sentence_token_index": 0,
    "difficulty_level": null,
    "explanation": null,
    "pos_tag": null,
    "lemma": null,
    "is_grammar_marker": false
  },
  {
    "token_id": 125,
    "sentence_id": 5,
    "token_body": " ",
    "token_type": "space",
    "sentence_token_index": 1,
    "difficulty_level": null,
    "explanation": null,
    "pos_tag": null,
    "lemma": null,
    "is_grammar_marker": false
  },
  {
    "token_id": 126,
    "sentence_id": 5,
    "token_body": "future",
    "token_type": "text",
    "sentence_token_index": 2,
    "difficulty_level": null,
    "explanation": null,
    "pos_tag": null,
    "lemma": null,
    "is_grammar_marker": false
  },
  {
    "token_id": 127,
    "sentence_id": 5,
    "token_body": " ",
    "token_type": "space",
    "sentence_token_index": 3,
    "difficulty_level": null,
    "explanation": null,
    "pos_tag": null,
    "lemma": null,
    "is_grammar_marker": false
  },
  {
    "token_id": 128,
    "sentence_id": 5,
    "token_body": "of",
    "token_type": "text",
    "sentence_token_index": 4,
    "difficulty_level": null,
    "explanation": null,
    "pos_tag": null,
    "lemma": null,
    "is_grammar_marker": false
  },
  {
    "token_id": 129,
    "sentence_id": 5,
    "token_body": " ",
    "token_type": "space",
    "sentence_token_index": 5,
    "difficulty_level": null,
    "explanation": null,
    "pos_tag": null,
    "lemma": null,
    "is_grammar_marker": false
  },
  {
    "token_id": 130,
    "sentence_id": 5,
    "token_body": "AI",
    "token_type": "text",
    "sentence_token_index": 6,
    "difficulty_level": null,
    "explanation": null,
    "pos_tag": null,
    "lemma": null,
    "is_grammar_marker": false
  },
  {
    "token_id": 131,
    "sentence_id": 5,
    "token_body": " ",
    "token_type": "space",
    "sentence_token_index": 7,
    "difficulty_level": null,
    "explanation": null,
    "pos_tag": null,
    "lemma": null,
    "is_grammar_marker": false
  },
  {
    "token_id": 132,
    "sentence_id": 5,
    "token_body": "promises",
    "token_type": "text",
    "sentence_token_index": 8,
    "difficulty_level": null,
    "explanation": null,
    "pos_tag": null,
    "lemma": null,
    "is_grammar_marker": false
  },
  {
    "token_id": 133,
    "sentence_id": 5,
    "token_body": " ",
    "token_type": "space",
    "sentence_token_index": 9,
    "difficulty_level": null,
    "explanation": null,
    "pos_tag": null,
    "lemma": null,
    "is_grammar_marker": false
  },
  {
    "token_id": 134,
    "sentence_id": 5,
    "token_body": "even",
    "token_type": "text",
    "sentence_token_index": 10,
    "difficulty_level": null,
    "explanation": null,
    "pos_tag": null,
    "lemma": null,
    "is_grammar_marker": false
  },
  {
    "token_id": 135,
    "sentence_id": 5,
    "token_body": " ",
    "token_type": "space",
    "sentence_token_index": 11,
    "difficulty_level": null,
    "explanation": null,
    "pos_tag": null,
    "lemma": null,
    "is_grammar_marker": false
  },
  {
    "token_id": 136,
    "sentence_id": 5,
    "token_body": "more",
    "token_type": "text",
    "sentence_token_index": 12,
    "difficulty_level": null,
    "explanation": null,
    "pos_tag": null,
    "lemma": null,
    "is_grammar_marker": false
  },
  {
    "token_id": 137,
    "sentence_id": 5,
    "token_body": " ",
    "token_type": "space",
    "sentence_token_index": 13,
    "difficulty_level": null,
    "explanation": null,
    "pos_tag": null,
    "lemma": null,
    "is_grammar_marker": false
  },
  {
    "token_id": 138,
    "sentence_id": 5,
    "token_body": "transformative",
    "token_type": "text",
    "sentence_token_index": 14,
    "difficulty_level": null,
    "explanation": null,
    "pos_tag": null,
    "lemma": null,
    "is_grammar_marker": false
  },
  {
    "token_id": 139,
    "sentence_id": 5,
    "token_body": " ",
    "token_type": "space",
    "sentence_token_index": 15,
    "difficulty_level": null,
    "explanation": null,
    "pos_tag": null,
    "lemma": null,
    "is_grammar_marker": false
  },
  {
    "token_id": 140,
    "sentence_id": 5,
    "token_body": "applications",
    "token_type": "text",
    "sentence_token_index": 16,
    "difficulty_level": null,
    "explanation": null,
    "pos_tag": null,
    "lemma": null,
    "is_grammar_marker": false
  },
  {
    "token_id": 141,
    "sentence_id": 5,
    "token_body": " ",
    "token_type": "space",
    "sentence_token_index": 17,
    "difficulty_level": null,
    "explanation": null,
    "pos_tag": null,
    "lemma": null,
    "is_grammar_marker": false
  },
  {
    "token_id": 142,
    "sentence_id": 5,
    "token_body": "across",
    "token_type": "text",
    "sentence_token_index": 18,
    "difficulty_level": null,
    "explanation": null,
    "pos_tag": null,
    "lemma": null,
    "is_grammar_marker": false
  },
  {
    "token_id": 143,
    "sentence_id": 5,
    "token_body": " ",
    "token_type": "space",
    "sentence_token_index": 19,
    "difficulty_level": null,
    "explanation": null,
    "pos_tag": null,
    "lemma": null,
    "is_grammar_marker": false
  },
  {
    "token_id": 144,
    "sentence_id": 5,
    "token_body": "healthcare",
    "token_type": "text",
    "sentence_token_index": 20,
    "difficulty_level": null,
    "explanation": null,
    "pos_tag": null,
    "lemma": null,
    "is_grammar_marker": false
  },
  {
    "token_id": 145,
    "sentence_id": 5,
    "token_body": ",",
    "token_type": "punctuation",
    "sentence_token_index": 21,
    "difficulty_level": null,
    "explanation": null,
    "pos_tag": null,
    "lemma": null,
    "is_grammar_marker": false
  },
  {
    "token_id": 146,
    "sentence_id": 5,
    "token_body": " ",
    "token_type": "space",
    "sentence_token_index": 22,
    "difficulty_level": null,
    "explanation": null,
    "pos_tag": null,
    "lemma": null,
    "is_grammar_marker": false
  },
  {
    "token_id": 147,
    "sentence_id": 5,
    "token_body": "education",
    "token_type": "text",
    "sentence_token_index": 23,
    "difficulty_level": null,
    "explanation": null,
    "pos_tag": null,
    "lemma": null,
    "is_grammar_marker": false
  },
  {
    "token_id": 148,
    "sentence_id": 5,
    "token_body": ",",
    "token_type": "punctuation",
    "sentence_token_index": 24,
    "difficulty_level": null,
    "explanation": null,
    "pos_tag": null,
    "lemma": null,
    "is_grammar_marker": false
  },
  {
    "token_id": 149,
    "sentence_id": 5,
    "token_body": " ",
    "token_type": "space",
    "sentence_token_index": 25,
    "difficulty_level": null,
    "explanation": null,
    "pos_tag": null,
    "lemma": null,
    "is_grammar_marker": false
  },
  {
    "token_id": 150,
    "sentence_id": 5,
    "token_body": "transportation",
    "token_type": "text",
    "sentence_token_index": 26,
    "difficulty_level": null,
    "explanation": null,
    "pos_tag": null,
    "lemma": null,
    "is_grammar_marker": false
  },
  {
    "token_id": 151,
    "sentence_id": 5,
    "token_body": ",",
    "token_type": "punctuation",
    "sentence_token_index": 27,
    "difficulty_level": null,
    "explanation": null,
    "pos_tag": null,
    "lemma": null,
    "is_grammar_marker": false
  },
  {
    "token_id": 152,
    "sentence_id": 5,
    "token_body": " ",
    "token_type": "space",
    "sentence_token_index": 28,
    "difficulty_level": null,
    "explanation": null,
    "pos_tag": null,
    "lemma": null,
    "is_grammar_marker": false
  },
  {
    "token_id": 153,
    "sentence_id": 5,
    "token_body": "and",
    "token_type": "text",
    "sentence_token_index": 29,
    "difficulty_level": null,
    "explanation": null,
    "pos_tag": null,
    "lemma": null,
    "is_grammar_marker": false
  },
  {
    "token_id": 154,
    "sentence_id": 5,
    "token_body": " ",
    "token_type": "space",
    "sentence_token_index": 30,
    "difficulty_level": null,
    "explanation": null,
    "pos_tag": null,
    "lemma": null,
    "is_grammar_marker": false
  },
  {
    "token_id": 155,
    "sentence_id": 5,
    "token_body": "entertainment",
    "token_type": "text",
    "sentence_token_index": 31,
    "difficulty_level": null,
    "explanation": null,
    "pos_tag": null,
    "lemma": null,
    "is_grammar_marker": false
  },
  {
    "token_id": 156,
    "sentence_id": 5,
    "token_body": " ",
    "token_type": "space",
    "sentence_token_index": 32,
    "difficulty_level": null,
    "explanation": null,
    "pos_tag": null,
    "lemma": null,
    "is_grammar_marker": false
  },
  {
    "token_id": 157,
    "sentence_id": 5,
    "token_body": "industries",
    "token_type": "text",
    "sentence_token_index": 33,
    "difficulty_level": null,
    "explanation": null,
    "pos_tag": null,
    "lemma": null,
    "is_grammar_marker": false
  },
  {
    "token_id": 158,
    "sentence_id": 5,
    "token_body": ".",
    "token_type": "punctuation",
    "sentence_token_index": 34,
    "difficulty_level": null,
    "explanation": null,
    "pos_tag": null,
    "lemma": null,
    "is_grammar_marker": false
  }
]